envy.py
django_envy-0.1.1.dist-info/DESCRIPTION.rst
django_envy-0.1.1.dist-info/LICENSE.txt
django_envy-0.1.1.dist-info/METADATA
django_envy-0.1.1.dist-info/RECORD
django_envy-0.1.1.dist-info/WHEEL
django_envy-0.1.1.dist-info/metadata.json
django_envy-0.1.1.dist-info/top_level.txt
